turftopic/__init__.py
turftopic/_concept_browser.py
turftopic/_datamapplot.py
turftopic/_figure.py
turftopic/analyzers/__init__.py
turftopic/analyzers/base.py
turftopic/analyzers/hf_llm.py
turftopic/analyzers/openai.py
turftopic/analyzers/t5.py
turftopic/analyzers/utc.py
turftopic/base.py
turftopic/container.py
turftopic/data.py
turftopic/dynamic.py
turftopic/encoders/__init__.py
turftopic/encoders/base.py
turftopic/encoders/cohere.py
turftopic/encoders/multimodal.py
turftopic/encoders/openai.py
turftopic/encoders/utils.py
turftopic/encoders/voyage.py
turftopic/error.py
turftopic/feature_importance.py
turftopic/hierarchical.py
turftopic/model_comparison/__init__.py
turftopic/model_comparison/embedding_metrics.py
turftopic/models/__init__.py
turftopic/models/_attentionmf.py
turftopic/models/_colbert.py
turftopic/models/_fastopic.py
turftopic/models/_gaussian_lda.py
turftopic/models/_hierarchical_clusters.py
turftopic/models/_keynmf.py
turftopic/models/_snmf.py
turftopic/models/cluster.py
turftopic/models/ctm.py
turftopic/models/decomp.py
turftopic/models/fastopic.py
turftopic/models/gmm.py
turftopic/models/keynmf.py
turftopic/models/senstopic.py
turftopic/models/topeax.py
turftopic/models/wnmf.py
turftopic/multimodal.py
turftopic/namers/__init__.py
turftopic/optimization.py
turftopic/serialization.py
turftopic/types.py
turftopic/utils.py
turftopic/vectorizers/__init__.py
turftopic/vectorizers/chinese.py
turftopic/vectorizers/default.py
turftopic/vectorizers/snowball.py
turftopic/vectorizers/spacy.py
turftopic-0.23.2.dist-info/LICENSE
turftopic-0.23.2.dist-info/METADATA
turftopic-0.23.2.dist-info/WHEEL
turftopic-0.23.2.dist-info/RECORD
