Metadata-Version: 2.3
Name: turftopic
Version: 0.23.2
Summary: Topic modeling with contextual representations from sentence transformers.
License: MIT
Author: Márton Kardos
Author-email: power.up1163@gmail.com> <martonkardos@cas.au.dk
Requires-Python: >=3.10
Classifier: License :: OSI Approved :: MIT License
Classifier: Programming Language :: Python :: 3
Classifier: Programming Language :: Python :: 3.10
Classifier: Programming Language :: Python :: 3.11
Classifier: Programming Language :: Python :: 3.12
Classifier: Programming Language :: Python :: 3.13
Provides-Extra: datamapplot
Provides-Extra: dev
Provides-Extra: docs
Provides-Extra: jieba
Provides-Extra: openai
Provides-Extra: pyro-ppl
Provides-Extra: snowball
Provides-Extra: spacy
Provides-Extra: topic-wizard
Provides-Extra: umap-learn
Requires-Dist: datamapplot (>=0.4.2,<1.0.0) ; extra == "datamapplot"
Requires-Dist: datamapplot (>=0.4.2,<1.0.0) ; extra == "dev"
Requires-Dist: datasets (>=4.3.0) ; extra == "dev"
Requires-Dist: griffe (==0.40.0) ; extra == "dev"
Requires-Dist: griffe (==0.40.0) ; extra == "docs"
Requires-Dist: huggingface-hub (>=0.23.2,<1.0.0)
Requires-Dist: igraph (>=0.11.6,<0.12.0)
Requires-Dist: jieba (>=0.40.0,<1.0.0) ; extra == "dev"
Requires-Dist: jieba (>=0.40.0,<1.0.0) ; extra == "jieba"
Requires-Dist: joblib (>=1.2.0,<2.0.0)
Requires-Dist: mkdocs (==1.5.3) ; extra == "dev"
Requires-Dist: mkdocs (==1.6.1) ; extra == "docs"
Requires-Dist: mkdocs-autorefs (==0.5.0) ; extra == "dev"
Requires-Dist: mkdocs-autorefs (==0.5.0) ; extra == "docs"
Requires-Dist: mkdocs-material (==9.5.6) ; extra == "dev"
Requires-Dist: mkdocs-material (==9.6.19) ; extra == "docs"
Requires-Dist: mkdocs-material-extensions (==1.3.1) ; extra == "dev"
Requires-Dist: mkdocs-material-extensions (==1.3.1) ; extra == "docs"
Requires-Dist: mkdocstrings (==0.22.0) ; extra == "dev"
Requires-Dist: mkdocstrings (==0.22.0) ; extra == "docs"
Requires-Dist: mkdocstrings-python (==1.8.0) ; extra == "dev"
Requires-Dist: mkdocstrings-python (==1.8.0) ; extra == "docs"
Requires-Dist: numpy (>=1.23.0)
Requires-Dist: openai (>=1.40.0,<2.0.0) ; extra == "dev"
Requires-Dist: openai (>=1.40.0,<2.0.0) ; extra == "openai"
Requires-Dist: pillow (>=10.4.0,<10.5.0)
Requires-Dist: pyro-ppl (>=1.8.0,<2.0.0) ; extra == "dev"
Requires-Dist: pyro-ppl (>=1.8.0,<2.0.0) ; extra == "pyro-ppl"
Requires-Dist: rich (>=13.6.0,<14.0.0)
Requires-Dist: scikit-learn (>=1.3.0,<2.0.0)
Requires-Dist: scipy (>=1.10.0,<2.0.0)
Requires-Dist: sentence-transformers (>=2.2.0)
Requires-Dist: snowballstemmer (>=2.0.0,<3.0.0) ; extra == "dev"
Requires-Dist: snowballstemmer (>=2.0.0,<3.0.0) ; extra == "snowball"
Requires-Dist: spacy (>=3.6.0,<4.0.0) ; extra == "spacy"
Requires-Dist: topic-wizard (>1.0.0,<2.0.0) ; extra == "dev"
Requires-Dist: topic-wizard (>1.0.0,<2.0.0) ; extra == "topic-wizard"
Requires-Dist: torch (>=2.1.0,<3.0.0)
Requires-Dist: umap-learn (>=0.5.5,<1.0.0) ; extra == "dev"
Requires-Dist: umap-learn (>=0.5.5,<1.0.0) ; extra == "umap-learn"
